pygifconvt_test_jl/__init__.py
pygifconvt_test_jl/converter.py
pygifconvt_test_jl-1.0.0.dist-info/LICENSE
pygifconvt_test_jl-1.0.0.dist-info/METADATA
pygifconvt_test_jl-1.0.0.dist-info/WHEEL
pygifconvt_test_jl-1.0.0.dist-info/top_level.txt
pygifconvt_test_jl-1.0.0.dist-info/RECORD
